{
  "annotations": [
    {
      "start_time": 0,
      "end_time": 7,
      "annotation": [
        {
          "type": "paragraph",
          "children": [
            {
              "text": "This is a download from the BBC. For details of our huge new range of audio for free download"
            }
          ]
        }
      ],
      "tags": [],
      "uuid": "bb127b78-1af6-448e-8a7d-1af347ea2757"
    },
    {
      "start_time": 7,
      "end_time": 14,
      "annotation": [
        {
          "type": "paragraph",
          "children": [
            {
              "text": "or podcast and our terms of use, go to bbcworldservice.com slash podcast."
            }
          ]
        }
      ],
      "tags": [],
      "uuid": "e823390b-af66-4225-8c67-b566e3d1896d"
    },
    {
      "start_time": 23,
      "end_time": 29,
      "annotation": [
        {
          "type": "paragraph",
          "children": [
            {
              "text": "The army takeover and its corrective mission had raised the hopes of our people in their"
            }
          ]
        }
      ],
      "tags": [],
      "uuid": "4482b429-35d0-4709-bffb-fcff8158d5b0"
    },
    {
      "start_time": 29,
      "end_time": 36,
      "annotation": [
        {
          "type": "paragraph",
          "children": [
            {
              "text": "desire to see an end to the hideous evils of tribalism, corruption and nepotism. The"
            }
          ]
        }
      ],
      "tags": [],
      "uuid": "d876b455-f154-4752-b8ab-3dec2cffba53"
    },
    {
      "start_time": 37,
      "end_time": 43,
      "annotation": [
        {
          "type": "paragraph",
          "children": [
            {
              "text": "army had professed to turn Nigeria into a land where no one should feel a stranger in"
            }
          ]
        }
      ],
      "tags": [],
      "uuid": "be050544-c8bb-445b-b5ba-bfae2e905ac7"
    },
    {
      "start_time": 43,
      "end_time": 50,
      "annotation": [
        {
          "type": "paragraph",
          "children": [
            {
              "text": "his own country. Sad to relate, the events of May, July and September 1966 and thereafter"
            }
          ]
        }
      ],
      "tags": [],
      "uuid": "ea5e842b-afb1-4c11-914c-800a9d52df4d"
    },
    {
      "start_time": 50,
      "end_time": 57,
      "annotation": [
        {
          "type": "paragraph",
          "children": [
            {
              "text": "have since shattered those pious hopes and plunged Nigeria into uncertainty, drift and"
            }
          ]
        }
      ],
      "tags": [],
      "uuid": "abf4b4a6-2100-4381-b97c-3b8f2fc114ea"
    },
    {
      "start_time": 60,
      "end_time": 67,
      "annotation": [
        {
          "type": "paragraph",
          "children": [
            {
              "text": "confusion. Wanton and premeditated acts of destruction against this region and its peoples"
            }
          ]
        }
      ],
      "tags": [],
      "uuid": "29357045-8a70-4152-845e-c4ec41395621"
    },
    {
      "start_time": 68,
      "end_time": 73,
      "annotation": [
        {
          "type": "paragraph",
          "children": [
            {
              "text": "have compelled them to reappraise their attitudes."
            }
          ]
        }
      ],
      "tags": [],
      "uuid": "53115f42-c688-4d4d-b574-c5dff277656f"
    },
    {
      "start_time": 73,
      "end_time": 80,
      "annotation": [
        {
          "type": "paragraph",
          "children": [
            {
              "text": "I am Wali Srinika, standing on that same Nigerian soil where, from the beginning of the 19th"
            }
          ]
        }
      ],
      "tags": [],
      "uuid": "8b65d1fe-866c-4884-a7f2-5ccb6d564b1e"
    },
    {
      "start_time": 80,
      "end_time": 86,
      "annotation": [
        {
          "type": "paragraph",
          "children": [
            {
              "text": "century to 40 years ago, what was perhaps the first full blown civil war in post-colonial"
            }
          ]
        }
      ],
      "tags": [],
      "uuid": "5039b9f1-03aa-452d-a74e-8a95de84dd34"
    },
    {
      "start_time": 86,
      "end_time": 91,
      "annotation": [
        {
          "type": "paragraph",
          "children": [
            {
              "text": "Africa took place."
            }
          ]
        }
      ],
      "tags": [],
      "uuid": "359d4677-40ff-40a4-878b-92201fcb1205"
    },
    {
      "start_time": 91,
      "end_time": 98,
      "annotation": [
        {
          "type": "paragraph",
          "children": [
            {
              "text": "The soldiers here say that from a yellow house which I can just see above the palm trees"
            }
          ]
        }
      ],
      "tags": [],
      "uuid": "80e537e2-af9c-45b8-a4e5-b0bad314164a"
    },
    {
      "start_time": 98,
      "end_time": 101,
      "annotation": [
        {
          "type": "paragraph",
          "children": [
            {
              "text": "has come a great deal of stiping fire this morning."
            }
          ]
        }
      ],
      "tags": [],
      "uuid": "ab8b9fe4-342d-4c6a-b988-e468532ce44e"
    },
    {
      "start_time": 101,
      "end_time": 107,
      "annotation": [
        {
          "type": "paragraph",
          "children": [
            {
              "text": "I saw on the roads thousands and thousands of refugees trying to bring a few possessions"
            }
          ]
        }
      ],
      "tags": [],
      "uuid": "6ce745b8-9c70-456b-8845-dc24be15d310"
    },
    {
      "start_time": 107,
      "end_time": 113,
      "annotation": [
        {
          "type": "paragraph",
          "children": [
            {
              "text": "and their children along with them. Word came that there had been a bombing raid on"
            }
          ]
        }
      ],
      "tags": [],
      "uuid": "80132a9b-64f0-4015-8d44-90abb2f41ec2"
    },
    {
      "start_time": 113,
      "end_time": 120,
      "annotation": [
        {
          "type": "paragraph",
          "children": [
            {
              "text": "a marketplace and I counted personally 65 dead bodies, many of which were charred beyond"
            }
          ]
        }
      ],
      "tags": [],
      "uuid": "6b46c065-2099-4f28-9c60-663539153686"
    },
    {
      "start_time": 122,
      "end_time": 127,
      "annotation": [
        {
          "type": "paragraph",
          "children": [
            {
              "text": "recognition."
            }
          ]
        }
      ],
      "tags": [],
      "uuid": "cff3f796-70e6-4440-ac5f-2c3bca09a798"
    },
    {
      "start_time": 127,
      "end_time": 131,
      "annotation": [
        {
          "type": "paragraph",
          "children": [
            {
              "text": "Following the first ever Nigerian military coup in January 1966 and its counter-coup"
            }
          ]
        }
      ],
      "tags": [],
      "uuid": "f96020c1-7fb6-47d6-b1a9-d7c9d2bc02ae"
    },
    {
      "start_time": 131,
      "end_time": 138,
      "annotation": [
        {
          "type": "paragraph",
          "children": [
            {
              "text": "in May, a young northern officer from a minority Christian group, Yakuba Gawan, ended up as"
            }
          ]
        }
      ],
      "tags": [],
      "uuid": "2811903c-4a7f-4dc3-a7d3-ecb2d1154a3a"
    },
    {
      "start_time": 138,
      "end_time": 143,
      "annotation": [
        {
          "type": "paragraph",
          "children": [
            {
              "text": "Nigeria's new head of state. The discovery of oil in huge reserves in the east played"
            }
          ]
        }
      ],
      "tags": [],
      "uuid": "f2f0a105-649b-4ec9-a97d-d7b70eb49ce1"
    },
    {
      "start_time": 143,
      "end_time": 148,
      "annotation": [
        {
          "type": "paragraph",
          "children": [
            {
              "text": "a role in the propulsion of the Biafran leaders towards secession. But it was not just the"
            }
          ]
        }
      ],
      "tags": [],
      "uuid": "ab87284b-c2af-4335-89db-99496d6a163e"
    },
    {
      "start_time": 148,
      "end_time": 154,
      "annotation": [
        {
          "type": "paragraph",
          "children": [
            {
              "text": "glare of oil wealth that drove the Igbo as a people to seek a separate existence led"
            }
          ]
        }
      ],
      "tags": [],
      "uuid": "2f1cff78-7898-4fa9-a2cc-e27993b167d9"
    },
    {
      "start_time": 154,
      "end_time": 161,
      "annotation": [
        {
          "type": "paragraph",
          "children": [
            {
              "text": "by Lieutenant Colonel Odumegu Ujuku, then military governor of the eastern region. The"
            }
          ]
        }
      ],
      "tags": [],
      "uuid": "782ce9d1-558b-4744-b185-653705de13b4"
    },
    {
      "start_time": 161,
      "end_time": 168,
      "annotation": [
        {
          "type": "paragraph",
          "children": [
            {
              "text": "prospect of war between the east and the federation loomed larger every day, propelled by statements"
            }
          ]
        }
      ],
      "tags": [],
      "uuid": "5c0f4867-b805-4fe8-bb0e-98e1d9f6d9a7"
    },
    {
      "start_time": 168,
      "end_time": 173,
      "annotation": [
        {
          "type": "paragraph",
          "children": [
            {
              "text": "from Ujuku which pointed the way to the breakup of Nigeria."
            }
          ]
        }
      ],
      "tags": [],
      "uuid": "d9bd4794-9945-4cc9-92ed-e2daa07a3c51"
    },
    {
      "start_time": 173,
      "end_time": 180,
      "annotation": [
        {
          "type": "paragraph",
          "children": [
            {
              "text": "We have reached a stage where I am unalterably convinced that to save the very semblance"
            }
          ]
        }
      ],
      "tags": [],
      "uuid": "6dbea42e-cad4-4d7d-9089-dc1cec7301e9"
    },
    {
      "start_time": 180,
      "end_time": 187,
      "annotation": [
        {
          "type": "paragraph",
          "children": [
            {
              "text": "of Nigeria as one country we must drift a little apart, call it confederation or a loose"
            }
          ]
        }
      ],
      "tags": [],
      "uuid": "28897f76-d123-4f0b-b8d1-78e49e010dfa"
    },
    {
      "start_time": 188,
      "end_time": 195,
      "annotation": [
        {
          "type": "paragraph",
          "children": [
            {
              "text": "association or whatever you will. It is the only way for survival, not only for ourselves"
            }
          ]
        }
      ],
      "tags": [],
      "uuid": "3a2424cb-408b-40be-ab65-3f8179cff609"
    },
    {
      "start_time": 196,
      "end_time": 198,
      "annotation": [
        {
          "type": "paragraph",
          "children": [
            {
              "text": "but also for the country."
            }
          ]
        }
      ],
      "tags": [],
      "uuid": "69a47cdb-9cbd-4092-8deb-4dc99fb5ed8f"
    },
    {
      "start_time": 198,
      "end_time": 205,
      "annotation": [
        {
          "type": "paragraph",
          "children": [
            {
              "text": "Ujuku declared an independent state of Biafran on May 30th 1967. I was in London with fellow"
            }
          ]
        }
      ],
      "tags": [],
      "uuid": "9e4340a2-b2ed-4448-b730-8f8df118a695"
    },
    {
      "start_time": 207,
      "end_time": 214,
      "annotation": [
        {
          "type": "paragraph",
          "children": [
            {
              "text": "Nigerians. We decided that someone had to go to the east to talk with Ujuku, a dangerous"
            }
          ]
        }
      ],
      "tags": [],
      "uuid": "fb4b0153-bd47-47fe-b3e0-5c3730f8f674"
    },
    {
      "start_time": 214,
      "end_time": 221,
      "annotation": [
        {
          "type": "paragraph",
          "children": [
            {
              "text": "mission as it was difficult for a non-Biafran to enter the now xenophobic entity called"
            }
          ]
        }
      ],
      "tags": [],
      "uuid": "57f69566-34c6-4d97-9915-66d417baa775"
    },
    {
      "start_time": 221,
      "end_time": 227,
      "annotation": [
        {
          "type": "paragraph",
          "children": [
            {
              "text": "Biafran. But I volunteered to go, to make the journey first from Lagos to the mid-west,"
            }
          ]
        }
      ],
      "tags": [],
      "uuid": "125af622-5a18-4d5e-b044-dbbfb010986e"
    },
    {
      "start_time": 227,
      "end_time": 233,
      "annotation": [
        {
          "type": "paragraph",
          "children": [
            {
              "text": "separated from the seceded state by the River Niger, then across into Biafran itself and"
            }
          ]
        }
      ],
      "tags": [],
      "uuid": "9f5c6405-fefc-4a0f-a79d-93733d6ec282"
    },
    {
      "start_time": 233,
      "end_time": 240,
      "annotation": [
        {
          "type": "paragraph",
          "children": [
            {
              "text": "the centre of power in Enugu. When I told a friend the plan, he choked on his meal."
            }
          ]
        }
      ],
      "tags": [],
      "uuid": "6f55bd93-0017-4e74-887c-19909288157d"
    },
    {
      "start_time": 241,
      "end_time": 247,
      "annotation": [
        {
          "type": "paragraph",
          "children": [
            {
              "text": "Madness, madness, nothing but madness, you get shot for nothing. But I made that journey"
            }
          ]
        }
      ],
      "tags": [],
      "uuid": "e1d65a29-27b1-4ed4-9999-f010a65b3dbb"
    },
    {
      "start_time": 247,
      "end_time": 254,
      "annotation": [
        {
          "type": "paragraph",
          "children": [
            {
              "text": "and today I am retracing my steps, going back to see Udumego Ujuku again after 40 years."
            }
          ]
        }
      ],
      "tags": [],
      "uuid": "7ec38bb1-833a-457a-8620-dc54cf099ac0"
    },
    {
      "start_time": 256,
      "end_time": 263,
      "annotation": [
        {
          "type": "paragraph",
          "children": [
            {
              "text": "The first stage takes me to the border of Biafran, the River Niger at Asaba."
            }
          ]
        }
      ],
      "tags": [],
      "uuid": "a54bc08d-3670-4779-8eb9-a891e9f01b22"
    },
    {
      "start_time": 270,
      "end_time": 277,
      "annotation": [
        {
          "type": "paragraph",
          "children": [
            {
              "text": "So we are on the west side of what is known as the Asaba bridge which links the mainly"
            }
          ]
        }
      ],
      "tags": [],
      "uuid": "8ef1f54f-ca9c-418f-b0a1-07f080ec8cf2"
    },
    {
      "start_time": 284,
      "end_time": 291,
      "annotation": [
        {
          "type": "paragraph",
          "children": [
            {
              "text": "Ibo west with the Ibo east, that is links Asaba on the west side with Onicha on the"
            }
          ]
        }
      ],
      "tags": [],
      "uuid": "ebda1745-1dd7-432f-84eb-770b2e9fa44b"
    },
    {
      "start_time": 293,
      "end_time": 300,
      "annotation": [
        {
          "type": "paragraph",
          "children": [
            {
              "text": "east side. And it was cut of course during the civil war. Before that of course, the"
            }
          ]
        }
      ],
      "tags": [],
      "uuid": "82fd80d7-e073-488a-920f-5b85f7faf51b"
    },
    {
      "start_time": 301,
      "end_time": 308,
      "annotation": [
        {
          "type": "paragraph",
          "children": [
            {
              "text": "was blocked on both sides by huge caterpillars, in effect trying to, in the attempt of the"
            }
          ]
        }
      ],
      "tags": [],
      "uuid": "c8efc632-479a-4037-b9f2-2e5e95467661"
    },
    {
      "start_time": 309,
      "end_time": 316,
      "annotation": [
        {
          "type": "paragraph",
          "children": [
            {
              "text": "federal side, to blockade the east and bring the secessionist section to heel. Now when"
            }
          ]
        }
      ],
      "tags": [],
      "uuid": "0d5cceee-61aa-43e1-ad69-9967bff2b647"
    },
    {
      "start_time": 316,
      "end_time": 323,
      "annotation": [
        {
          "type": "paragraph",
          "children": [
            {
              "text": "I crossed, I remember I crossed much further, which is south now, south is this way yes,"
            }
          ]
        }
      ],
      "tags": [],
      "uuid": "72ec3588-7e27-4687-945a-b5c751c132e7"
    },
    {
      "start_time": 323,
      "end_time": 330,
      "annotation": [
        {
          "type": "paragraph",
          "children": [
            {
              "text": "as the crossing point was further south from where canoes took off across the Niger River"
            }
          ]
        }
      ],
      "tags": [],
      "uuid": "abc1cb33-8b22-4385-82ef-7a2b6b632f90"
    },
    {
      "start_time": 330,
      "end_time": 337,
      "annotation": [
        {
          "type": "paragraph",
          "children": [
            {
              "text": "to the other side. Before crossing the river, I spent the night"
            }
          ]
        }
      ],
      "tags": [],
      "uuid": "764360a5-7c53-49c3-b035-27497513dc96"
    },
    {
      "start_time": 337,
      "end_time": 344,
      "annotation": [
        {
          "type": "paragraph",
          "children": [
            {
              "text": "in Asaba as a guest of Professor Edozine. Today he is His Highness the Asagba of Asaba"
            }
          ]
        }
      ],
      "tags": [],
      "uuid": "540ed342-54f6-432a-af1b-dc168ee98df4"
    },
    {
      "start_time": 344,
      "end_time": 351,
      "annotation": [
        {
          "type": "paragraph",
          "children": [
            {
              "text": "Edozine. It is a privilege to see him again and following the traditional greetings in"
            }
          ]
        }
      ],
      "tags": [],
      "uuid": "821d0f01-7dd8-44db-a689-d0b405078a96"
    },
    {
      "start_time": 351,
      "end_time": 358,
      "annotation": [
        {
          "type": "paragraph",
          "children": [
            {
              "text": "his royal reception hall to hear both from him and distinguished residents in Asaba of"
            }
          ]
        }
      ],
      "tags": [],
      "uuid": "b3b10c75-1302-4611-a8f7-72db4edb5640"
    },
    {
      "start_time": 358,
      "end_time": 363,
      "annotation": [
        {
          "type": "paragraph",
          "children": [
            {
              "text": "the events that happened during the Biafran war."
            }
          ]
        }
      ],
      "tags": [],
      "uuid": "f867415c-d68a-4b85-881d-75b313380bbb"
    },
    {
      "start_time": 363,
      "end_time": 370,
      "annotation": [
        {
          "type": "paragraph",
          "children": [
            {
              "text": "There was the first wave of killing and after that it died down and there was peace. From"
            }
          ]
        }
      ],
      "tags": [],
      "uuid": "c05acb20-488c-452b-8475-ef7cf8af6327"
    },
    {
      "start_time": 372,
      "end_time": 379,
      "annotation": [
        {
          "type": "paragraph",
          "children": [
            {
              "text": "my understanding that on a certain day the people were persuaded to go to the border"
            }
          ]
        }
      ],
      "tags": [],
      "uuid": "42a018c9-8d4d-4e79-81de-9a6534f1ce7c"
    },
    {
      "start_time": 381,
      "end_time": 388,
      "annotation": [
        {
          "type": "paragraph",
          "children": [
            {
              "text": "and they were told that if they come to welcome the federal troops that the killings will"
            }
          ]
        }
      ],
      "tags": [],
      "uuid": "8a52606d-b309-4cb5-8a18-6754ebf55960"
    },
    {
      "start_time": 388,
      "end_time": 395,
      "annotation": [
        {
          "type": "paragraph",
          "children": [
            {
              "text": "stop. So the people gathered and danced and invited the federal troops to welcome, instead"
            }
          ]
        }
      ],
      "tags": [],
      "uuid": "a23cb670-d3c4-4594-84fa-30cbe2e85060"
    },
    {
      "start_time": 396,
      "end_time": 403,
      "annotation": [
        {
          "type": "paragraph",
          "children": [
            {
              "text": "of welcome, said men on this side, women on that side and they gunned down the men."
            }
          ]
        }
      ],
      "tags": [],
      "uuid": "daf12c6e-cd7a-49a5-8e20-b0c429982bab"
    },
    {
      "start_time": 403,
      "end_time": 410,
      "annotation": [
        {
          "type": "paragraph",
          "children": [
            {
              "text": "They had actually started killing people when I now again moved to Biafran inside"
            }
          ]
        }
      ],
      "tags": [],
      "uuid": "313f56a2-3055-4068-954e-53fcef060e86"
    },
    {
      "start_time": 410,
      "end_time": 417,
      "annotation": [
        {
          "type": "paragraph",
          "children": [
            {
              "text": "to Nubu and then to Port Harcourt and then I was there until the war ended. The point"
            }
          ]
        }
      ],
      "tags": [],
      "uuid": "9fd3012c-31f3-441d-9f41-3752bd2b2fcd"
    },
    {
      "start_time": 417,
      "end_time": 424,
      "annotation": [
        {
          "type": "paragraph",
          "children": [
            {
              "text": "I want to bring out is that yes, the troops were involved but they could not have done"
            }
          ]
        }
      ],
      "tags": [],
      "uuid": "7357a4d3-d6f5-4855-87c6-7b7a1ad91c6c"
    },
    {
      "start_time": 424,
      "end_time": 431,
      "annotation": [
        {
          "type": "paragraph",
          "children": [
            {
              "text": "that without involvement of some civilians who wanted to get some revenge or something"
            }
          ]
        }
      ],
      "tags": [],
      "uuid": "08288043-4cf3-4b39-a960-1654aa923e49"
    },
    {
      "start_time": 431,
      "end_time": 432,
      "annotation": [
        {
          "type": "paragraph",
          "children": [
            {
              "text": "like that."
            }
          ]
        }
      ],
      "tags": [],
      "uuid": "af234758-eafc-4637-b58e-155f0069b4f0"
    },
    {
      "start_time": 432,
      "end_time": 443,
      "annotation": [
        {
          "type": "paragraph",
          "children": [
            {
              "text": "But when the federal troops came they didn't ask questions. There was general killing of"
            }
          ]
        }
      ],
      "tags": [],
      "uuid": "45d0a623-3e86-4404-ad6b-b7208705c199"
    },
    {
      "start_time": 444,
      "end_time": 451,
      "annotation": [
        {
          "type": "paragraph",
          "children": [
            {
              "text": "our people, our houses were bombed, men, women, actually. It was a tragedy. We all had to"
            }
          ]
        }
      ],
      "tags": [],
      "uuid": "8fd984c3-2b9c-4715-914d-2a2b47f57246"
    },
    {
      "start_time": 491,
      "end_time": 498,
      "annotation": [
        {
          "type": "paragraph",
          "children": [
            {
              "text": "be together. I saw an Aleutian bomber supplied by the Russians of the Federal Nigerian Air"
            }
          ]
        }
      ],
      "tags": [],
      "uuid": "d0c7338d-07b8-477e-8f20-abdbe7410c8c"
    },
    {
      "start_time": 498,
      "end_time": 505,
      "annotation": [
        {
          "type": "paragraph",
          "children": [
            {
              "text": "Force come in and make its slow run in from the north. I was on the spot within five minutes"
            }
          ]
        }
      ],
      "tags": [],
      "uuid": "704ba661-a1a6-4430-9838-6b2ad8e0814b"
    },
    {
      "start_time": 506,
      "end_time": 513,
      "annotation": [
        {
          "type": "paragraph",
          "children": [
            {
              "text": "and saw the bodies of a young mother and her infant child being lifted, they were naked,"
            }
          ]
        }
      ],
      "tags": [],
      "uuid": "ffb882b1-0e78-4074-9129-13ba61f2676d"
    },
    {
      "start_time": 514,
      "end_time": 521,
      "annotation": [
        {
          "type": "paragraph",
          "children": [
            {
              "text": "they were dead, being lifted onto a piece of corrugated iron roofing which was used"
            }
          ]
        }
      ],
      "tags": [],
      "uuid": "86331160-2205-45f7-8c45-7aede29a3df5"
    },
    {
      "start_time": 521,
      "end_time": 525,
      "annotation": [
        {
          "type": "paragraph",
          "children": [
            {
              "text": "to serve as a stretcher."
            }
          ]
        }
      ],
      "tags": [],
      "uuid": "ec0a7686-f648-4978-a41f-70eec5d7a876"
    },
    {
      "start_time": 531,
      "end_time": 538,
      "annotation": [
        {
          "type": "paragraph",
          "children": [
            {
              "text": "You're listening to the BBC World Service with me, Walis Shonnka, returning to Biafran."
            }
          ]
        }
      ],
      "tags": [],
      "uuid": "24812823-14f6-4d2a-90f9-09d8ae84afe3"
    },
    {
      "start_time": 539,
      "end_time": 545,
      "annotation": [
        {
          "type": "paragraph",
          "children": [
            {
              "text": "Although Biafran was supposed to be under a blockade and Asabah Bridge was blocked on"
            }
          ]
        }
      ],
      "tags": [],
      "uuid": "f52bd6fd-aad7-4366-8896-9e2931470353"
    },
    {
      "start_time": 545,
      "end_time": 552,
      "annotation": [
        {
          "type": "paragraph",
          "children": [
            {
              "text": "both the Midwest and the secessionist sides, traffic, both human and goods, flowed both"
            }
          ]
        }
      ],
      "tags": [],
      "uuid": "2d7a7128-ff0a-4a93-bde2-ba95157517fb"
    },
    {
      "start_time": 552,
      "end_time": 559,
      "annotation": [
        {
          "type": "paragraph",
          "children": [
            {
              "text": "ways. I crossed the River Niger by canoe and arrived in Onitsha, the twin city to Asabah,"
            }
          ]
        }
      ],
      "tags": [],
      "uuid": "ebb3e232-b79c-412c-8f31-ac9a878af84b"
    },
    {
      "start_time": 559,
      "end_time": 563,
      "annotation": [
        {
          "type": "paragraph",
          "children": [
            {
              "text": "where it passed through the busy effervescent market."
            }
          ]
        }
      ],
      "tags": [],
      "uuid": "b05af9c8-168d-4cb0-b8c0-77789aa3545c"
    },
    {
      "start_time": 563,
      "end_time": 569,
      "annotation": [
        {
          "type": "paragraph",
          "children": [
            {
              "text": "Let me talk. I go on. Yes, we know this man very well. When I did primary six, Professor"
            }
          ]
        }
      ],
      "tags": [],
      "uuid": "376467bd-6d50-476e-813e-7a6f3b373117"
    },
    {
      "start_time": 569,
      "end_time": 574,
      "annotation": [
        {
          "type": "paragraph",
          "children": [
            {
              "text": "Oyoinka, I know him when I was in primary six. Bro, God bless you."
            }
          ]
        }
      ],
      "tags": [],
      "uuid": "74c84c19-3526-4af5-9281-cfb6b0ab7233"
    },
    {
      "start_time": 582,
      "end_time": 589,
      "annotation": [
        {
          "type": "paragraph",
          "children": [
            {
              "text": "Just as when I appeared here a few moments ago, there was lots of recognition and people"
            }
          ]
        }
      ],
      "tags": [],
      "uuid": "40ccf876-6196-4efe-9318-42e66fff7a6a"
    },
    {
      "start_time": 589,
      "end_time": 595,
      "annotation": [
        {
          "type": "paragraph",
          "children": [
            {
              "text": "saw exactly the same situation at that time. There was lots of recognition and people stopped"
            }
          ]
        }
      ],
      "tags": [],
      "uuid": "3a801670-d69e-42c0-9704-5bdc964ed2da"
    },
    {
      "start_time": 595,
      "end_time": 599,
      "annotation": [
        {
          "type": "paragraph",
          "children": [
            {
              "text": "to say hello, some stopped to ask news of what was happening on the other side, but"
            }
          ]
        }
      ],
      "tags": [],
      "uuid": "f6a57df9-0556-460e-b3db-3b96429b73d7"
    },
    {
      "start_time": 599,
      "end_time": 605,
      "annotation": [
        {
          "type": "paragraph",
          "children": [
            {
              "text": "of course there were the vigilantes. I met some and they let me go. Eventually there"
            }
          ]
        }
      ],
      "tags": [],
      "uuid": "f5cceea6-2241-4ea2-8c12-a3468ce2d1a0"
    },
    {
      "start_time": 605,
      "end_time": 612,
      "annotation": [
        {
          "type": "paragraph",
          "children": [
            {
              "text": "came this group of very young vigilantes with wooden guns and pointed the wooden guns at"
            }
          ]
        }
      ],
      "tags": [],
      "uuid": "1a4ab251-625c-4c67-8355-ac35f1b8d53d"
    },
    {
      "start_time": 612,
      "end_time": 619,
      "annotation": [
        {
          "type": "paragraph",
          "children": [
            {
              "text": "me and insisted on identifying myself. So I identified myself and said, well, what do"
            }
          ]
        }
      ],
      "tags": [],
      "uuid": "10ba4717-71ca-4fdf-b730-67642869a0ae"
    },
    {
      "start_time": 619,
      "end_time": 625,
      "annotation": [
        {
          "type": "paragraph",
          "children": [
            {
              "text": "you do on this side? I said, well, I came to see you people and to see Emeka Ojupu and"
            }
          ]
        }
      ],
      "tags": [],
      "uuid": "1ebfaed7-f80b-4cbf-be08-809a74e22c9a"
    },
    {
      "start_time": 625,
      "end_time": 632,
      "annotation": [
        {
          "type": "paragraph",
          "children": [
            {
              "text": "Tusho, you know, searched me. Very, very excitable. For me, what was most amusing and at the same"
            }
          ]
        }
      ],
      "tags": [],
      "uuid": "41e4c2a5-334c-45fb-b836-ba64a58dc348"
    },
    {
      "start_time": 632,
      "end_time": 637,
      "annotation": [
        {
          "type": "paragraph",
          "children": [
            {
              "text": "time rather pathetic and sad was the fact that they handled those wooden guns as if"
            }
          ]
        }
      ],
      "tags": [],
      "uuid": "ff86f0b9-d941-4ac6-82a8-95b943b24b24"
    },
    {
      "start_time": 637,
      "end_time": 645,
      "annotation": [
        {
          "type": "paragraph",
          "children": [
            {
              "text": "they were real guns, as if they believed in them. And it sort of was a kind of portent"
            }
          ]
        }
      ],
      "tags": [],
      "uuid": "371eeb43-cabe-4fee-a7c3-b1cd8e964fac"
    },
    {
      "start_time": 645,
      "end_time": 653,
      "annotation": [
        {
          "type": "paragraph",
          "children": [
            {
              "text": "of what was to come that this was a people really unprepared for war, but with absolute faith."
            }
          ]
        }
      ],
      "tags": [],
      "uuid": "1574ea65-0b9e-4ee7-83d4-3b7b0cafabc6"
    },
    {
      "start_time": 667,
      "end_time": 679,
      "annotation": [
        {
          "type": "paragraph",
          "children": [
            {
              "text": "This evening there will be a meeting for prayer and dedication for the Republic of"
            }
          ]
        }
      ],
      "tags": [],
      "uuid": "c072b3d6-ebcd-415d-8274-8ab1c4b8cfe0"
    },
    {
      "start_time": 679,
      "end_time": 685,
      "annotation": [
        {
          "type": "paragraph",
          "children": [
            {
              "text": "Biafra, sponsored jointly by the Roman Catholic and Christian Council Churches at the Endugu"
            }
          ]
        }
      ],
      "tags": [],
      "uuid": "7a16edb9-8834-4802-b786-e2ae36d9b5c7"
    },
    {
      "start_time": 685,
      "end_time": 692,
      "annotation": [
        {
          "type": "paragraph",
          "children": [
            {
              "text": "Sports Stadium. Although our present difficulties have partly arisen because some people in"
            }
          ]
        }
      ],
      "tags": [],
      "uuid": "10aadca6-a01b-4d31-b9a2-e938ac5ec81f"
    },
    {
      "start_time": 692,
      "end_time": 698,
      "annotation": [
        {
          "type": "paragraph",
          "children": [
            {
              "text": "what used to be called the Federation of Nigeria believe that God's world is too small"
            }
          ]
        }
      ],
      "tags": [],
      "uuid": "86ca39d7-52a8-4ba7-baf6-788bec894b05"
    },
    {
      "start_time": 698,
      "end_time": 706,
      "annotation": [
        {
          "type": "paragraph",
          "children": [
            {
              "text": "for mankind to live in, yet the encouraging fact of our age is the increase in discovery"
            }
          ]
        }
      ],
      "tags": [],
      "uuid": "8c7cba13-f135-4558-92ed-05f77dedab82"
    },
    {
      "start_time": 706,
      "end_time": 713,
      "annotation": [
        {
          "type": "paragraph",
          "children": [
            {
              "text": "on the part of many Biafra that we are all one in the Lord Jesus Christ. Let me remind"
            }
          ]
        }
      ],
      "tags": [],
      "uuid": "3a509ba1-3790-4412-a309-4d04df615e26"
    },
    {
      "start_time": 713,
      "end_time": 719,
      "annotation": [
        {
          "type": "paragraph",
          "children": [
            {
              "text": "you that you are listening to Radio Biafra broadcasting from the Endugu Sports Stadium."
            }
          ]
        }
      ],
      "tags": [],
      "uuid": "f5fe2148-89c9-465d-87d4-a16edae9015c"
    },
    {
      "start_time": 719,
      "end_time": 726,
      "annotation": [
        {
          "type": "paragraph",
          "children": [
            {
              "text": "I was arrested, but generally well treated, and brought my passport with me to make all"
            }
          ]
        }
      ],
      "tags": [],
      "uuid": "e8687c74-3bb8-4577-9c14-7ee0a2bfd785"
    },
    {
      "start_time": 726,
      "end_time": 733,
      "annotation": [
        {
          "type": "paragraph",
          "children": [
            {
              "text": "understand that I accepted that I was visiting a sovereign territory. Transferred for interrogation"
            }
          ]
        }
      ],
      "tags": [],
      "uuid": "c8501173-0566-47bc-b83f-a12e9504bfb8"
    },
    {
      "start_time": 733,
      "end_time": 740,
      "annotation": [
        {
          "type": "paragraph",
          "children": [
            {
              "text": "to Endugu, now elevated from a regional to a national capital, I was routinely locked"
            }
          ]
        }
      ],
      "tags": [],
      "uuid": "fa546c65-79c1-4289-92b8-bb1e9bdc7bde"
    },
    {
      "start_time": 740,
      "end_time": 747,
      "annotation": [
        {
          "type": "paragraph",
          "children": [
            {
              "text": "up in a police cell, treated as a regular suspect, all possessions confiscated, belt,"
            }
          ]
        }
      ],
      "tags": [],
      "uuid": "256f1114-7895-48a9-9c71-3d6aeb7cda07"
    },
    {
      "start_time": 747,
      "end_time": 765,
      "annotation": [
        {
          "type": "paragraph",
          "children": [
            {
              "text": "shoes and underpants taken away. The hotel presidential, where I was lodged as a guest"
            }
          ]
        }
      ],
      "tags": [],
      "uuid": "9267591d-ccea-4718-9368-6be1d4db0490"
    },
    {
      "start_time": 765,
      "end_time": 772,
      "annotation": [
        {
          "type": "paragraph",
          "children": [
            {
              "text": "of the government, said it all. Sanctions and a blockade to enforce them had taken their"
            }
          ]
        }
      ],
      "tags": [],
      "uuid": "debc2ae9-4801-4c2c-8b09-9e7d6796f60d"
    },
    {
      "start_time": 772,
      "end_time": 778,
      "annotation": [
        {
          "type": "paragraph",
          "children": [
            {
              "text": "role, and this once splendid lodging with a commanding view of the city had nothing"
            }
          ]
        }
      ],
      "tags": [],
      "uuid": "aa864eaa-f921-433e-b0e0-bf1cd4188419"
    },
    {
      "start_time": 778,
      "end_time": 786,
      "annotation": [
        {
          "type": "paragraph",
          "children": [
            {
              "text": "left that was remotely presidential, except perhaps the size of its rats. If I sought"
            }
          ]
        }
      ],
      "tags": [],
      "uuid": "3ffe2c9b-3a87-45d3-9eef-4f4c2f9dcacc"
    },
    {
      "start_time": 786,
      "end_time": 794,
      "annotation": [
        {
          "type": "paragraph",
          "children": [
            {
              "text": "a pessimistic portent for the future of Biafra, the presidential offered itself most assertively."
            }
          ]
        }
      ],
      "tags": [],
      "uuid": "592e080b-03e5-46db-bab7-3eec9ac42044"
    },
    {
      "start_time": 794,
      "end_time": 801,
      "annotation": [
        {
          "type": "paragraph",
          "children": [
            {
              "text": "I tried my best to dismiss this pessimistic image, however. I eyeballed the rats while"
            }
          ]
        }
      ],
      "tags": [],
      "uuid": "2c87ad0c-8a81-46cc-868c-2a49b8171042"
    },
    {
      "start_time": 801,
      "end_time": 808,
      "annotation": [
        {
          "type": "paragraph",
          "children": [
            {
              "text": "awaiting my summons to the leader of the secessionist state."
            }
          ]
        }
      ],
      "tags": [],
      "uuid": "179943cf-1487-4177-86cb-2734947b5d72"
    },
    {
      "start_time": 808,
      "end_time": 817,
      "annotation": [
        {
          "type": "paragraph",
          "children": [
            {
              "text": "Nigeria can never be the same again, of that we are sure. If it is to remain one entity,"
            }
          ]
        }
      ],
      "tags": [],
      "uuid": "ae1c5709-a8cc-4bfd-b7bd-ec1f5d772d45"
    },
    {
      "start_time": 817,
      "end_time": 826,
      "annotation": [
        {
          "type": "paragraph",
          "children": [
            {
              "text": "everyone must wake up from the stupor and work hard and fast to reach a realistic solution."
            }
          ]
        }
      ],
      "tags": [],
      "uuid": "ec78d2bd-5321-489f-9fa3-be19d3b13ed0"
    },
    {
      "start_time": 826,
      "end_time": 832,
      "annotation": [
        {
          "type": "paragraph",
          "children": [
            {
              "text": "Otherwise, we cannot avoid disintegration."
            }
          ]
        }
      ],
      "tags": [],
      "uuid": "fbbbd132-0f06-492b-b6af-640acf58daa0"
    },
    {
      "start_time": 832,
      "end_time": 838,
      "annotation": [
        {
          "type": "paragraph",
          "children": [
            {
              "text": "For this return journey to the former state of Biafra, my ultimate destination remained"
            }
          ]
        }
      ],
      "tags": [],
      "uuid": "0caa26a0-8438-49d3-87c9-527d792ba710"
    },
    {
      "start_time": 838,
      "end_time": 845,
      "annotation": [
        {
          "type": "paragraph",
          "children": [
            {
              "text": "the same, to meet and speak with the secessionist leader, Odunegu Ojoku. This time, however,"
            }
          ]
        }
      ],
      "tags": [],
      "uuid": "76cf6657-c370-4833-ba8c-c32242e8f8da"
    },
    {
      "start_time": 845,
      "end_time": 852,
      "annotation": [
        {
          "type": "paragraph",
          "children": [
            {
              "text": "I also planned to meet with representatives of the younger generation who refused to abandon"
            }
          ]
        }
      ],
      "tags": [],
      "uuid": "5aa0d7af-ea6a-45d5-93ca-5edce283d29b"
    },
    {
      "start_time": 852,
      "end_time": 859,
      "annotation": [
        {
          "type": "paragraph",
          "children": [
            {
              "text": "the dream of Biafra. These have organized themselves into a movement known as MASOB"
            }
          ]
        }
      ],
      "tags": [],
      "uuid": "eedc64b0-2005-4e5b-aa26-9af5c9b224b2"
    },
    {
      "start_time": 859,
      "end_time": 865,
      "annotation": [
        {
          "type": "paragraph",
          "children": [
            {
              "text": "– Movement for the Actualization of the Sovereign State of Biafra. Meeting their leaders"
            }
          ]
        }
      ],
      "tags": [],
      "uuid": "3e9f9505-a307-4ede-bc61-3b24d0f65548"
    },
    {
      "start_time": 865,
      "end_time": 871,
      "annotation": [
        {
          "type": "paragraph",
          "children": [
            {
              "text": "did not prove quite as easy as was earlier promised. They had gone underground, following"
            }
          ]
        }
      ],
      "tags": [],
      "uuid": "b82f89ae-3157-4533-8ae0-15f2b78257d9"
    },
    {
      "start_time": 871,
      "end_time": 877,
      "annotation": [
        {
          "type": "paragraph",
          "children": [
            {
              "text": "information that military and police action against them was imminent. First, though,"
            }
          ]
        }
      ],
      "tags": [],
      "uuid": "aea61026-b591-40ea-8157-1513e8c3955d"
    },
    {
      "start_time": 877,
      "end_time": 884,
      "annotation": [
        {
          "type": "paragraph",
          "children": [
            {
              "text": "a chance to speak again with Odunegu Ojoku, the leader I came to meet forty years ago."
            }
          ]
        }
      ],
      "tags": [],
      "uuid": "e74c5b7a-de0e-4ab8-9e97-e03f72ea3528"
    },
    {
      "start_time": 884,
      "end_time": 891,
      "annotation": [
        {
          "type": "paragraph",
          "children": [
            {
              "text": "With failing eyesight, he is still as passionate as ever about the cause. And he can remember"
            }
          ]
        }
      ],
      "tags": [],
      "uuid": "db49263f-49bf-44f2-b332-c14bc962937b"
    },
    {
      "start_time": 891,
      "end_time": 894,
      "annotation": [
        {
          "type": "paragraph",
          "children": [
            {
              "text": "the day arrived in 1967."
            }
          ]
        }
      ],
      "tags": [],
      "uuid": "8a2149f9-9a3c-48c1-bb4a-c0f8abbaf644"
    },
    {
      "start_time": 894,
      "end_time": 906,
      "annotation": [
        {
          "type": "paragraph",
          "children": [
            {
              "text": "My immediate feeling was that my father, who has done it again, has come in. He doesn't"
            }
          ]
        }
      ],
      "tags": [],
      "uuid": "bd791d29-e07e-41cd-bdbf-a6650636b492"
    },
    {
      "start_time": 906,
      "end_time": 917,
      "annotation": [
        {
          "type": "paragraph",
          "children": [
            {
              "text": "know what problem he's got me into, because I needed to protect you. You were Yoruba,"
            }
          ]
        }
      ],
      "tags": [],
      "uuid": "4ebe49cc-96cf-4351-95ad-854687f7a1ff"
    },
    {
      "start_time": 917,
      "end_time": 927,
      "annotation": [
        {
          "type": "paragraph",
          "children": [
            {
              "text": "you're coming in. People had to decide, do they embrace you or hit you across the head?"
            }
          ]
        }
      ],
      "tags": [],
      "uuid": "2364248e-e579-415a-9bf5-c849402552ef"
    },
    {
      "start_time": 927,
      "end_time": 933,
      "annotation": [
        {
          "type": "paragraph",
          "children": [
            {
              "text": "I was worried I thought they might hit you, but actually you're very lucky."
            }
          ]
        }
      ],
      "tags": [],
      "uuid": "c0eaf7b3-364a-4c52-b11c-83b186757906"
    },
    {
      "start_time": 933,
      "end_time": 941,
      "annotation": [
        {
          "type": "paragraph",
          "children": [
            {
              "text": "I counted on the fact of human curiosity. Somebody deliberately came into what was supposed"
            }
          ]
        }
      ],
      "tags": [],
      "uuid": "5c16a73b-2118-4779-bac0-65f5af3020eb"
    },
    {
      "start_time": 941,
      "end_time": 948,
      "annotation": [
        {
          "type": "paragraph",
          "children": [
            {
              "text": "to be an enemy. I was very confident that I would get to see a responsible person as"
            }
          ]
        }
      ],
      "tags": [],
      "uuid": "be1df967-8f6d-4290-a38d-8c02aa0c45cd"
    },
    {
      "start_time": 948,
      "end_time": 954,
      "annotation": [
        {
          "type": "paragraph",
          "children": [
            {
              "text": "soon as possible. I got where I was headed, so I had no qualms whatsoever. None."
            }
          ]
        }
      ],
      "tags": [],
      "uuid": "1f234927-88bc-49e8-8802-da94c0971f2d"
    },
    {
      "start_time": 954,
      "end_time": 964,
      "annotation": [
        {
          "type": "paragraph",
          "children": [
            {
              "text": "You had no qualms. I sat on a hot stool, wondering what would happen. I found it was the beginning"
            }
          ]
        }
      ],
      "tags": [],
      "uuid": "a06fb210-971a-4aee-929b-8050f03e956f"
    },
    {
      "start_time": 964,
      "end_time": 972,
      "annotation": [
        {
          "type": "paragraph",
          "children": [
            {
              "text": "of what I suffered. I went through throughout the war. My own view on many things, quite"
            }
          ]
        }
      ],
      "tags": [],
      "uuid": "2c1ab8a3-408d-4b28-808e-2ae1f56a4b6a"
    },
    {
      "start_time": 972,
      "end_time": 982,
      "annotation": [
        {
          "type": "paragraph",
          "children": [
            {
              "text": "different actually from the views of the Odunaru people. I had to explain that despite what"
            }
          ]
        }
      ],
      "tags": [],
      "uuid": "646f3da3-4ed4-4fb1-8d0c-e668e8ef0454"
    },
    {
      "start_time": 982,
      "end_time": 987,
      "annotation": [
        {
          "type": "paragraph",
          "children": [
            {
              "text": "was going on, I still had unconsidered certain Yorubas as friends."
            }
          ]
        }
      ],
      "tags": [],
      "uuid": "31183302-6ca9-4a7b-8e6a-7728f6f3b1b7"
    },
    {
      "start_time": 987,
      "end_time": 995,
      "annotation": [
        {
          "type": "paragraph",
          "children": [
            {
              "text": "Ojoku still holds his position from 1967. I asked him about the decision to secede and"
            }
          ]
        }
      ],
      "tags": [],
      "uuid": "673aad99-75d4-4373-b82d-20f2c91e8fef"
    },
    {
      "start_time": 995,
      "end_time": 997,
      "annotation": [
        {
          "type": "paragraph",
          "children": [
            {
              "text": "how it actually came about."
            }
          ]
        }
      ],
      "tags": [],
      "uuid": "fc35f8cd-4881-4687-9842-9bd2954ead11"
    },
    {
      "start_time": 997,
      "end_time": 1008,
      "annotation": [
        {
          "type": "paragraph",
          "children": [
            {
              "text": "We on this side, the eastern side, believe in Nigeria. We have proven that we've shown"
            }
          ]
        }
      ],
      "tags": [],
      "uuid": "52440984-7444-46da-a867-d3dd86330e4a"
    },
    {
      "start_time": 1008,
      "end_time": 1017,
      "annotation": [
        {
          "type": "paragraph",
          "children": [
            {
              "text": "it in so many ways. We have developed areas in Nigeria. We have been with Nigerians. We"
            }
          ]
        }
      ],
      "tags": [],
      "uuid": "9b8281ff-415d-4206-b1cf-dda07ce6d003"
    },
    {
      "start_time": 1017,
      "end_time": 1025,
      "annotation": [
        {
          "type": "paragraph",
          "children": [
            {
              "text": "continue to join Nigerians in everything. But there comes a point where if you push"
            }
          ]
        }
      ],
      "tags": [],
      "uuid": "56056e24-f997-4ce5-b513-ca1c0c928865"
    },
    {
      "start_time": 1025,
      "end_time": 1033,
      "annotation": [
        {
          "type": "paragraph",
          "children": [
            {
              "text": "us, we say, ah, enough is enough. If that is the price we have to pay for unity, then"
            }
          ]
        }
      ],
      "tags": [],
      "uuid": "5974309a-abec-4258-a4ed-8f90eb43b7ba"
    },
    {
      "start_time": 1033,
      "end_time": 1042,
      "annotation": [
        {
          "type": "paragraph",
          "children": [
            {
              "text": "it's better for us to stand alone. So that decision to secede, as you put it, you don't"
            }
          ]
        }
      ],
      "tags": [],
      "uuid": "07355d16-36fa-4b44-a1aa-ef55f4832e3c"
    },
    {
      "start_time": 1042,
      "end_time": 1048,
      "annotation": [
        {
          "type": "paragraph",
          "children": [
            {
              "text": "just sit down. We must secede. We didn't do that. But we were aware that there must"
            }
          ]
        }
      ],
      "tags": [],
      "uuid": "f9a3b1ab-b275-4673-8e26-9d865cae086b"
    },
    {
      "start_time": 1048,
      "end_time": 1057,
      "annotation": [
        {
          "type": "paragraph",
          "children": [
            {
              "text": "come a time if the other side continues along this line, then we have to face that. No matter"
            }
          ]
        }
      ],
      "tags": [],
      "uuid": "173b4059-8f16-4da9-92a3-577b3caba886"
    },
    {
      "start_time": 1057,
      "end_time": 1065,
      "annotation": [
        {
          "type": "paragraph",
          "children": [
            {
              "text": "how unpleasant or pleasant it appears to you, that is the point. We certainly were considering"
            }
          ]
        }
      ],
      "tags": [],
      "uuid": "a3bfefd0-a70c-48ad-8710-0d5191dd31d3"
    },
    {
      "start_time": 1065,
      "end_time": 1075,
      "annotation": [
        {
          "type": "paragraph",
          "children": [
            {
              "text": "it from the minute the massacres took place. You see how we can live if we're going to"
            }
          ]
        }
      ],
      "tags": [],
      "uuid": "abe28b76-4de9-4bb1-9099-29b638caf15a"
    },
    {
      "start_time": 1075,
      "end_time": 1077,
      "annotation": [
        {
          "type": "paragraph",
          "children": [
            {
              "text": "be massacred."
            }
          ]
        }
      ],
      "tags": [],
      "uuid": "e80b49ec-9f41-4ad7-a5b0-6ec21b98ad36"
    },
    {
      "start_time": 1077,
      "end_time": 1083,
      "annotation": [
        {
          "type": "paragraph",
          "children": [
            {
              "text": "There are certain things perhaps you might like to remember too. After the first massacre,"
            }
          ]
        }
      ],
      "tags": [],
      "uuid": "f073671f-0448-447e-af23-159bc76fa0d1"
    },
    {
      "start_time": 1084,
      "end_time": 1090,
      "annotation": [
        {
          "type": "paragraph",
          "children": [
            {
              "text": "I was the one that got onto the air and said to the Ibers, please, this is an aberration,"
            }
          ]
        }
      ],
      "tags": [],
      "uuid": "29788164-5a41-48a5-88c2-539c6bb5d843"
    },
    {
      "start_time": 1090,
      "end_time": 1093,
      "annotation": [
        {
          "type": "paragraph",
          "children": [
            {
              "text": "go back to the north. I was the one."
            }
          ]
        }
      ],
      "tags": [],
      "uuid": "20db2846-8798-48d6-b6f5-276f31244ad7"
    },
    {
      "start_time": 1093,
      "end_time": 1098,
      "annotation": [
        {
          "type": "paragraph",
          "children": [
            {
              "text": "I remember, I can't forget that if I was going to come to that. I was going to, and I'll"
            }
          ]
        }
      ],
      "tags": [],
      "uuid": "5469aa7d-6651-4b65-8724-46b639e8b319"
    },
    {
      "start_time": 1098,
      "end_time": 1104,
      "annotation": [
        {
          "type": "paragraph",
          "children": [
            {
              "text": "come to it in a minute because I wanted to ask you if you ever, you must have revisited"
            }
          ]
        }
      ],
      "tags": [],
      "uuid": "19440234-439c-4069-831b-9ecb55ccc00f"
    },
    {
      "start_time": 1104,
      "end_time": 1105,
      "annotation": [
        {
          "type": "paragraph",
          "children": [
            {
              "text": "that."
            }
          ]
        }
      ],
      "tags": [],
      "uuid": "a386bab0-2604-4593-8400-3e6dcc2a19dc"
    },
    {
      "start_time": 1105,
      "end_time": 1106,
      "annotation": [
        {
          "type": "paragraph",
          "children": [
            {
              "text": "Oh yes, all the time."
            }
          ]
        }
      ],
      "tags": [],
      "uuid": "aafa33f8-5bd6-40b0-8d87-a95b1ebeedda"
    },
    {
      "start_time": 1106,
      "end_time": 1109,
      "annotation": [
        {
          "type": "paragraph",
          "children": [
            {
              "text": "That is, you are lost of time and just how much anguish this must have caused you that"
            }
          ]
        }
      ],
      "tags": [],
      "uuid": "452f0307-9f3c-4027-9c73-c58b90f66e34"
    },
    {
      "start_time": 1109,
      "end_time": 1116,
      "annotation": [
        {
          "type": "paragraph",
          "children": [
            {
              "text": "you actually came out and said everybody go back, that you belong there, Nigeria. You"
            }
          ]
        }
      ],
      "tags": [],
      "uuid": "78ca4037-fa37-4565-8444-adf66c863578"
    },
    {
      "start_time": 1116,
      "end_time": 1119,
      "annotation": [
        {
          "type": "paragraph",
          "children": [
            {
              "text": "know, I can't forget that at all."
            }
          ]
        }
      ],
      "tags": [],
      "uuid": "0a5afaba-ccf0-489e-81fe-ebdf7baf14ba"
    },
    {
      "start_time": 1119,
      "end_time": 1123,
      "annotation": [
        {
          "type": "paragraph",
          "children": [
            {
              "text": "So, for the future, can Nigeria survive?"
            }
          ]
        }
      ],
      "tags": [],
      "uuid": "2e6c688f-5550-4493-9b0c-e0832aedbbd6"
    },
    {
      "start_time": 1123,
      "end_time": 1134,
      "annotation": [
        {
          "type": "paragraph",
          "children": [
            {
              "text": "If you want Nigeria, I don't think it's impossible. I don't at all. But you'll just have to train"
            }
          ]
        }
      ],
      "tags": [],
      "uuid": "ea6e7fb4-90e8-4c06-a892-829dd1676a96"
    },
    {
      "start_time": 1134,
      "end_time": 1142,
      "annotation": [
        {
          "type": "paragraph",
          "children": [
            {
              "text": "yourselves to really believing the equality of citizenship. If you're not prepared for"
            }
          ]
        }
      ],
      "tags": [],
      "uuid": "2d3b8387-46ec-4360-9152-96a8b92e566b"
    },
    {
      "start_time": 1142,
      "end_time": 1145,
      "annotation": [
        {
          "type": "paragraph",
          "children": [
            {
              "text": "it, forget Nigeria."
            }
          ]
        }
      ],
      "tags": [],
      "uuid": "667aa583-6523-4af9-8e65-b88a5cd0483c"
    },
    {
      "start_time": 1149,
      "end_time": 1154,
      "annotation": [
        {
          "type": "paragraph",
          "children": [
            {
              "text": "I'm Walishenka on a journey back to Biafra for the BBC World Service."
            }
          ]
        }
      ],
      "tags": [],
      "uuid": "1eddec62-15cc-4828-b251-405f0998d633"
    },
    {
      "start_time": 1154,
      "end_time": 1166,
      "annotation": [
        {
          "type": "paragraph",
          "children": [
            {
              "text": "It will be a great disservice for anyone to continue to use the word Biafra to refer"
            }
          ]
        }
      ],
      "tags": [],
      "uuid": "d93644e0-9428-4541-8029-ce716260413a"
    },
    {
      "start_time": 1166,
      "end_time": 1175,
      "annotation": [
        {
          "type": "paragraph",
          "children": [
            {
              "text": "to any part of the East Central State of Nigeria. The tragic chapter of violence has just ended."
            }
          ]
        }
      ],
      "tags": [],
      "uuid": "7906e749-ad3b-4976-b69e-bee7cf098b4a"
    },
    {
      "start_time": 1176,
      "end_time": 1184,
      "annotation": [
        {
          "type": "paragraph",
          "children": [
            {
              "text": "We are at the dawn of national reconciliation. Once again, we have an opportunity to build"
            }
          ]
        }
      ],
      "tags": [],
      "uuid": "9380841a-ab5e-43f4-8238-43c7ee7c18bc"
    },
    {
      "start_time": 1184,
      "end_time": 1186,
      "annotation": [
        {
          "type": "paragraph",
          "children": [
            {
              "text": "a new nation."
            }
          ]
        }
      ],
      "tags": [],
      "uuid": "22cc4e4f-12b4-48ee-9b70-7a258a7218b7"
    },
    {
      "start_time": 1190,
      "end_time": 1200,
      "annotation": [
        {
          "type": "paragraph",
          "children": [
            {
              "text": "Here we are finally outdoors at night with all the night sounds of Enugu. And one of"
            }
          ]
        }
      ],
      "tags": [],
      "uuid": "7436b7a4-b5f5-40d3-a6ad-3f2d8f08eddd"
    },
    {
      "start_time": 1200,
      "end_time": 1207,
      "annotation": [
        {
          "type": "paragraph",
          "children": [
            {
              "text": "the reasons we're actually at this spot, which is a rather secretive spot, is that"
            }
          ]
        }
      ],
      "tags": [],
      "uuid": "f312c64d-cc02-40b5-aca3-82252688a5b7"
    },
    {
      "start_time": 1207,
      "end_time": 1213,
      "annotation": [
        {
          "type": "paragraph",
          "children": [
            {
              "text": "the person I'm going to talk to now belongs to an organisation which is being hunted by"
            }
          ]
        }
      ],
      "tags": [],
      "uuid": "216cd7a9-c916-4c4b-b3e3-9a3101848218"
    },
    {
      "start_time": 1213,
      "end_time": 1220,
      "annotation": [
        {
          "type": "paragraph",
          "children": [
            {
              "text": "the police. The leader of that organisation has been in detention for nearly two years."
            }
          ]
        }
      ],
      "tags": [],
      "uuid": "931e362c-4d88-476b-a8d1-1c4b4f3d5eaa"
    },
    {
      "start_time": 1220,
      "end_time": 1226,
      "annotation": [
        {
          "type": "paragraph",
          "children": [
            {
              "text": "We're talking of MASA, by the way, the movement for the actualisation of Biafra. And I'll"
            }
          ]
        }
      ],
      "tags": [],
      "uuid": "2267af29-c7a3-42a6-bd2d-9970a7a91e7b"
    },
    {
      "start_time": 1226,
      "end_time": 1232,
      "annotation": [
        {
          "type": "paragraph",
          "children": [
            {
              "text": "ask you directly, what does Biafra mean to you, really?"
            }
          ]
        }
      ],
      "tags": [],
      "uuid": "b91793b9-aca3-4416-a404-396cf255ae14"
    },
    {
      "start_time": 1232,
      "end_time": 1241,
      "annotation": [
        {
          "type": "paragraph",
          "children": [
            {
              "text": "What it actually means to me is it is an identity because my great grandparents have been identified"
            }
          ]
        }
      ],
      "tags": [],
      "uuid": "807037de-28dd-4a53-978b-456ebfdd84af"
    },
    {
      "start_time": 1241,
      "end_time": 1247,
      "annotation": [
        {
          "type": "paragraph",
          "children": [
            {
              "text": "as Biafras even before the Portuguese, the British people and what have you, I mean the"
            }
          ]
        }
      ],
      "tags": [],
      "uuid": "32c838f0-3351-4d76-84e0-ab69805fd986"
    },
    {
      "start_time": 1247,
      "end_time": 1251,
      "annotation": [
        {
          "type": "paragraph",
          "children": [
            {
              "text": "white colonies, before they came down to this place. So what I'm trying to say right now"
            }
          ]
        }
      ],
      "tags": [],
      "uuid": "a526cb26-f8ab-4045-87c2-571f9aa8bb92"
    },
    {
      "start_time": 1251,
      "end_time": 1262,
      "annotation": [
        {
          "type": "paragraph",
          "children": [
            {
              "text": "is this, Biafra simply means to me what I am, naturally, by my culture, my language"
            }
          ]
        }
      ],
      "tags": [],
      "uuid": "5259108b-ca91-4d84-8f0f-76057f642dfb"
    },
    {
      "start_time": 1262,
      "end_time": 1268,
      "annotation": [
        {
          "type": "paragraph",
          "children": [
            {
              "text": "and my God's given right to live as a Biafra."
            }
          ]
        }
      ],
      "tags": [],
      "uuid": "14261f6f-c947-4505-a581-545f9942af69"
    },
    {
      "start_time": 1268,
      "end_time": 1279,
      "annotation": [
        {
          "type": "paragraph",
          "children": [
            {
              "text": "Does the actualisation mean for you secession from the Federation of Nigeria to which you"
            }
          ]
        }
      ],
      "tags": [],
      "uuid": "b05a2dcc-3cdd-49fd-ba54-959890ffb556"
    },
    {
      "start_time": 1279,
      "end_time": 1282,
      "annotation": [
        {
          "type": "paragraph",
          "children": [
            {
              "text": "at the moment, up till now, belong?"
            }
          ]
        }
      ],
      "tags": [],
      "uuid": "fb0474ca-4546-4b24-9a53-2a2a91ae4a30"
    },
    {
      "start_time": 1282,
      "end_time": 1287,
      "annotation": [
        {
          "type": "paragraph",
          "children": [
            {
              "text": "We are talking of Biafra today and the whole world has been hearing of Biafra and we claim"
            }
          ]
        }
      ],
      "tags": [],
      "uuid": "71d7cf3b-9049-489c-b080-fc3d57548da4"
    },
    {
      "start_time": 1287,
      "end_time": 1294,
      "annotation": [
        {
          "type": "paragraph",
          "children": [
            {
              "text": "to be Biafrans but one thing still remains, the sovereignty. So we cannot claim total"
            }
          ]
        }
      ],
      "tags": [],
      "uuid": "0fe072ae-ece8-4ea7-ae55-3b99216867a2"
    },
    {
      "start_time": 1294,
      "end_time": 1298,
      "annotation": [
        {
          "type": "paragraph",
          "children": [
            {
              "text": "freedom for now. But for the fact that we know we are Biafrans, we must keep claiming"
            }
          ]
        }
      ],
      "tags": [],
      "uuid": "e292f4c3-bac1-4d7a-a047-a27a4eea3742"
    },
    {
      "start_time": 1298,
      "end_time": 1304,
      "annotation": [
        {
          "type": "paragraph",
          "children": [
            {
              "text": "that. Till today, the Almighty will say, yes, this is the time for you to be free from your"
            }
          ]
        }
      ],
      "tags": [],
      "uuid": "67329544-3d35-4b74-8713-5664521b556f"
    },
    {
      "start_time": 1304,
      "end_time": 1310,
      "annotation": [
        {
          "type": "paragraph",
          "children": [
            {
              "text": "masters because we are like slaves right now and of course you know that. It's like"
            }
          ]
        }
      ],
      "tags": [],
      "uuid": "aeacca6c-5e27-4073-8474-aca8c8b4f628"
    },
    {
      "start_time": 1310,
      "end_time": 1316,
      "annotation": [
        {
          "type": "paragraph",
          "children": [
            {
              "text": "it is a thing that has been going on day in day out and it will continue like that till"
            }
          ]
        }
      ],
      "tags": [],
      "uuid": "44143deb-1f6e-4fb4-8f23-b1a6c323f18f"
    },
    {
      "start_time": 1316,
      "end_time": 1322,
      "annotation": [
        {
          "type": "paragraph",
          "children": [
            {
              "text": "the day we shall say hooray to the Almighty for giving us our freedom."
            }
          ]
        }
      ],
      "tags": [],
      "uuid": "ba06323d-97d0-4b42-9124-4f4da4d9a2d1"
    },
    {
      "start_time": 1322,
      "end_time": 1327,
      "annotation": [
        {
          "type": "paragraph",
          "children": [
            {
              "text": "Join me next week on the BBC World Service when I'll be completing my journey with a"
            }
          ]
        }
      ],
      "tags": [],
      "uuid": "4c7d7dc9-95fd-47ee-8327-96c0228273b4"
    },
    {
      "start_time": 1327,
      "end_time": 1334,
      "annotation": [
        {
          "type": "paragraph",
          "children": [
            {
              "text": "man to Lagos where I want to meet the man who put me behind bars for my audacious trip"
            }
          ]
        }
      ],
      "tags": [],
      "uuid": "c2054f6f-4700-4691-8199-a5d83d1bf005"
    },
    {
      "start_time": 1334,
      "end_time": 1335,
      "annotation": [
        {
          "type": "paragraph",
          "children": [
            {
              "text": "to Biafra."
            }
          ]
        }
      ],
      "tags": [],
      "uuid": "88416381-fea7-4573-9605-1e2b5c6d28cd"
    },
    {
      "start_time": 1335,
      "end_time": 1335,
      "annotation": [
        {
          "type": "paragraph",
          "children": [
            {
              "text": "1"
            }
          ]
        }
      ],
      "tags": [],
      "uuid": "66fbece5-c1cb-462b-87c5-92a889bbaf84"
    }
  ],
  "set": "Default",
  "event_id": "2c6fef11-1ab9-42ef-a557-adf304789dc5",
  "source_id": "d74f00d3-70d8-43b8-b8e9-0d16fdce21fc"
}